wit/__init__.py
wit/__main__.py
wit/common.py
wit/dependency.py
wit/env.py
wit/gitrepo.py
wit/inspect.py
wit/lock.py
wit/main.py
wit/manifest.py
wit/package.py
wit/parser.py
wit/repo_entries.py
wit/version.py
wit/witlogger.py
wit/workspace.py
wit_sifive-0.14.1.dist-info/METADATA
wit_sifive-0.14.1.dist-info/WHEEL
wit_sifive-0.14.1.dist-info/entry_points.txt
wit_sifive-0.14.1.dist-info/top_level.txt
wit_sifive-0.14.1.dist-info/RECORD
