Metadata-Version: 2.1
Name: wit-sifive
Version: 0.14.1
Summary: Wit: Workspace Integration Tool
Home-page: https://www.github.com/sifive/wit
Author: SiFive
Author-email: 
License: UNKNOWN
Platform: UNKNOWN
Classifier: License :: OSI Approved :: Apache Software License
Requires-Python: >=3.5
